{
  "id": "d0bdf390-e1c2-4597-841d-adaf2ebe0e13",
  "prevId": "0e0851a2-b088-42db-b3fb-86c28d8b9d3c",
  "version": "7",
  "dialect": "postgresql",
  "tables": {
    "public.admin_users": {
      "name": "admin_users",
      "schema": "",
      "columns": {
        "id": {
          "name": "id",
          "type": "serial",
          "primaryKey": true,
          "notNull": true
        },
        "email": {
          "name": "email",
          "type": "varchar(255)",
          "primaryKey": false,
          "notNull": true
        },
        "password_hash": {
          "name": "password_hash",
          "type": "text",
          "primaryKey": false,
          "notNull": true
        },
        "created_at": {
          "name": "created_at",
          "type": "timestamp",
          "primaryKey": false,
          "notNull": true,
          "default": "now()"
        }
      },
      "indexes": {},
      "foreignKeys": {},
      "compositePrimaryKeys": {},
      "uniqueConstraints": {
        "admin_users_email_unique": {
          "name": "admin_users_email_unique",
          "nullsNotDistinct": false,
          "columns": [
            "email"
          ]
        }
      },
      "policies": {},
      "checkConstraints": {},
      "isRLSEnabled": false
    },
    "public.calendarios_evaluaciones": {
      "name": "calendarios_evaluaciones",
      "schema": "",
      "columns": {
        "id": {
          "name": "id",
          "type": "serial",
          "primaryKey": true,
          "notNull": true
        },
        "curso": {
          "name": "curso",
          "type": "varchar(50)",
          "primaryKey": false,
          "notNull": true
        },
        "enlace": {
          "name": "enlace",
          "type": "text",
          "primaryKey": false,
          "notNull": false
        },
        "ciclo": {
          "name": "ciclo",
          "type": "varchar(50)",
          "primaryKey": false,
          "notNull": true
        },
        "orden": {
          "name": "orden",
          "type": "integer",
          "primaryKey": false,
          "notNull": true,
          "default": 0
        },
        "activo": {
          "name": "activo",
          "type": "boolean",
          "primaryKey": false,
          "notNull": true,
          "default": false
        },
        "created_at": {
          "name": "created_at",
          "type": "timestamp",
          "primaryKey": false,
          "notNull": true,
          "default": "now()"
        },
        "updated_at": {
          "name": "updated_at",
          "type": "timestamp",
          "primaryKey": false,
          "notNull": true,
          "default": "now()"
        }
      },
      "indexes": {},
      "foreignKeys": {},
      "compositePrimaryKeys": {},
      "uniqueConstraints": {},
      "policies": {},
      "checkConstraints": {},
      "isRLSEnabled": false
    },
    "public.centro_padres_directiva": {
      "name": "centro_padres_directiva",
      "schema": "",
      "columns": {
        "id": {
          "name": "id",
          "type": "serial",
          "primaryKey": true,
          "notNull": true
        },
        "nombre": {
          "name": "nombre",
          "type": "varchar(100)",
          "primaryKey": false,
          "notNull": true
        },
        "cargo": {
          "name": "cargo",
          "type": "varchar(80)",
          "primaryKey": false,
          "notNull": true
        },
        "foto_url": {
          "name": "foto_url",
          "type": "text",
          "primaryKey": false,
          "notNull": false
        },
        "email": {
          "name": "email",
          "type": "varchar(255)",
          "primaryKey": false,
          "notNull": false
        },
        "orden": {
          "name": "orden",
          "type": "integer",
          "primaryKey": false,
          "notNull": true,
          "default": 0
        },
        "periodo": {
          "name": "periodo",
          "type": "varchar(20)",
          "primaryKey": false,
          "notNull": false
        },
        "activo": {
          "name": "activo",
          "type": "boolean",
          "primaryKey": false,
          "notNull": true,
          "default": true
        },
        "created_at": {
          "name": "created_at",
          "type": "timestamp",
          "primaryKey": false,
          "notNull": true,
          "default": "now()"
        },
        "updated_at": {
          "name": "updated_at",
          "type": "timestamp",
          "primaryKey": false,
          "notNull": true,
          "default": "now()"
        }
      },
      "indexes": {},
      "foreignKeys": {},
      "compositePrimaryKeys": {},
      "uniqueConstraints": {},
      "policies": {},
      "checkConstraints": {},
      "isRLSEnabled": false
    },
    "public.centro_padres_documentos": {
      "name": "centro_padres_documentos",
      "schema": "",
      "columns": {
        "id": {
          "name": "id",
          "type": "serial",
          "primaryKey": true,
          "notNull": true
        },
        "titulo": {
          "name": "titulo",
          "type": "varchar(120)",
          "primaryKey": false,
          "notNull": true
        },
        "tipo": {
          "name": "tipo",
          "type": "varchar(20)",
          "primaryKey": false,
          "notNull": true
        },
        "archivo_url": {
          "name": "archivo_url",
          "type": "text",
          "primaryKey": false,
          "notNull": true
        },
        "fecha": {
          "name": "fecha",
          "type": "date",
          "primaryKey": false,
          "notNull": false
        },
        "created_at": {
          "name": "created_at",
          "type": "timestamp",
          "primaryKey": false,
          "notNull": true,
          "default": "now()"
        }
      },
      "indexes": {},
      "foreignKeys": {},
      "compositePrimaryKeys": {},
      "uniqueConstraints": {},
      "policies": {},
      "checkConstraints": {},
      "isRLSEnabled": false
    },
    "public.centro_padres_proyectos": {
      "name": "centro_padres_proyectos",
      "schema": "",
      "columns": {
        "id": {
          "name": "id",
          "type": "serial",
          "primaryKey": true,
          "notNull": true
        },
        "titulo": {
          "name": "titulo",
          "type": "varchar(120)",
          "primaryKey": false,
          "notNull": true
        },
        "descripcion": {
          "name": "descripcion",
          "type": "text",
          "primaryKey": false,
          "notNull": true
        },
        "estado": {
          "name": "estado",
          "type": "varchar(20)",
          "primaryKey": false,
          "notNull": true
        },
        "fecha_inicio": {
          "name": "fecha_inicio",
          "type": "date",
          "primaryKey": false,
          "notNull": false
        },
        "imagen_url": {
          "name": "imagen_url",
          "type": "text",
          "primaryKey": false,
          "notNull": false
        },
        "created_at": {
          "name": "created_at",
          "type": "timestamp",
          "primaryKey": false,
          "notNull": true,
          "default": "now()"
        },
        "updated_at": {
          "name": "updated_at",
          "type": "timestamp",
          "primaryKey": false,
          "notNull": true,
          "default": "now()"
        }
      },
      "indexes": {},
      "foreignKeys": {},
      "compositePrimaryKeys": {},
      "uniqueConstraints": {},
      "policies": {},
      "checkConstraints": {},
      "isRLSEnabled": false
    },
    "public.configuracion_sitio": {
      "name": "configuracion_sitio",
      "schema": "",
      "columns": {
        "id": {
          "name": "id",
          "type": "serial",
          "primaryKey": true,
          "notNull": true
        },
        "redes_sociales": {
          "name": "redes_sociales",
          "type": "jsonb",
          "primaryKey": false,
          "notNull": true,
          "default": "'[]'::jsonb"
        },
        "telefonos": {
          "name": "telefonos",
          "type": "jsonb",
          "primaryKey": false,
          "notNull": true,
          "default": "'[]'::jsonb"
        },
        "emails": {
          "name": "emails",
          "type": "jsonb",
          "primaryKey": false,
          "notNull": true,
          "default": "'[]'::jsonb"
        },
        "direccion": {
          "name": "direccion",
          "type": "text",
          "primaryKey": false,
          "notNull": false
        },
        "mapa_embed_url": {
          "name": "mapa_embed_url",
          "type": "text",
          "primaryKey": false,
          "notNull": false
        },
        "updated_at": {
          "name": "updated_at",
          "type": "timestamp",
          "primaryKey": false,
          "notNull": true,
          "default": "now()"
        }
      },
      "indexes": {},
      "foreignKeys": {},
      "compositePrimaryKeys": {},
      "uniqueConstraints": {},
      "policies": {},
      "checkConstraints": {},
      "isRLSEnabled": false
    },
    "public.coordinaciones": {
      "name": "coordinaciones",
      "schema": "",
      "columns": {
        "id": {
          "name": "id",
          "type": "serial",
          "primaryKey": true,
          "notNull": true
        },
        "nombre_unidad": {
          "name": "nombre_unidad",
          "type": "varchar(100)",
          "primaryKey": false,
          "notNull": true
        },
        "encargada": {
          "name": "encargada",
          "type": "varchar(100)",
          "primaryKey": false,
          "notNull": true
        },
        "titulo_profesional": {
          "name": "titulo_profesional",
          "type": "varchar(150)",
          "primaryKey": false,
          "notNull": false
        },
        "correo_institucional": {
          "name": "correo_institucional",
          "type": "varchar(255)",
          "primaryKey": false,
          "notNull": false
        },
        "foto_url": {
          "name": "foto_url",
          "type": "text",
          "primaryKey": false,
          "notNull": false
        },
        "funciones": {
          "name": "funciones",
          "type": "text",
          "primaryKey": false,
          "notNull": true
        },
        "resena_profesional": {
          "name": "resena_profesional",
          "type": "text",
          "primaryKey": false,
          "notNull": false
        },
        "orden": {
          "name": "orden",
          "type": "integer",
          "primaryKey": false,
          "notNull": true
        },
        "created_at": {
          "name": "created_at",
          "type": "timestamp",
          "primaryKey": false,
          "notNull": true,
          "default": "now()"
        },
        "updated_at": {
          "name": "updated_at",
          "type": "timestamp",
          "primaryKey": false,
          "notNull": true,
          "default": "now()"
        }
      },
      "indexes": {},
      "foreignKeys": {},
      "compositePrimaryKeys": {},
      "uniqueConstraints": {},
      "policies": {},
      "checkConstraints": {},
      "isRLSEnabled": false
    },
    "public.descargas": {
      "name": "descargas",
      "schema": "",
      "columns": {
        "id": {
          "name": "id",
          "type": "serial",
          "primaryKey": true,
          "notNull": true
        },
        "nombre": {
          "name": "nombre",
          "type": "varchar(100)",
          "primaryKey": false,
          "notNull": true
        },
        "categoria": {
          "name": "categoria",
          "type": "varchar(50)",
          "primaryKey": false,
          "notNull": true
        },
        "archivo_url": {
          "name": "archivo_url",
          "type": "text",
          "primaryKey": false,
          "notNull": true
        },
        "version": {
          "name": "version",
          "type": "varchar(20)",
          "primaryKey": false,
          "notNull": false
        },
        "imagen_url": {
          "name": "imagen_url",
          "type": "text",
          "primaryKey": false,
          "notNull": false
        },
        "color_acento": {
          "name": "color_acento",
          "type": "varchar(20)",
          "primaryKey": false,
          "notNull": true,
          "default": "'azul'"
        },
        "created_at": {
          "name": "created_at",
          "type": "timestamp",
          "primaryKey": false,
          "notNull": true,
          "default": "now()"
        },
        "updated_at": {
          "name": "updated_at",
          "type": "timestamp",
          "primaryKey": false,
          "notNull": true,
          "default": "now()"
        }
      },
      "indexes": {},
      "foreignKeys": {},
      "compositePrimaryKeys": {},
      "uniqueConstraints": {},
      "policies": {},
      "checkConstraints": {},
      "isRLSEnabled": false
    },
    "public.descargas_categorias": {
      "name": "descargas_categorias",
      "schema": "",
      "columns": {
        "id": {
          "name": "id",
          "type": "serial",
          "primaryKey": true,
          "notNull": true
        },
        "nombre": {
          "name": "nombre",
          "type": "varchar(100)",
          "primaryKey": false,
          "notNull": true
        },
        "orden": {
          "name": "orden",
          "type": "integer",
          "primaryKey": false,
          "notNull": true,
          "default": 0
        },
        "created_at": {
          "name": "created_at",
          "type": "timestamp",
          "primaryKey": false,
          "notNull": true,
          "default": "now()"
        }
      },
      "indexes": {},
      "foreignKeys": {},
      "compositePrimaryKeys": {},
      "uniqueConstraints": {},
      "policies": {},
      "checkConstraints": {},
      "isRLSEnabled": false
    },
    "public.eventos": {
      "name": "eventos",
      "schema": "",
      "columns": {
        "id": {
          "name": "id",
          "type": "serial",
          "primaryKey": true,
          "notNull": true
        },
        "nombre": {
          "name": "nombre",
          "type": "varchar(150)",
          "primaryKey": false,
          "notNull": true
        },
        "fecha": {
          "name": "fecha",
          "type": "date",
          "primaryKey": false,
          "notNull": true
        },
        "descripcion": {
          "name": "descripcion",
          "type": "varchar(200)",
          "primaryKey": false,
          "notNull": true
        },
        "tipo": {
          "name": "tipo",
          "type": "varchar(20)",
          "primaryKey": false,
          "notNull": true,
          "default": "'general'"
        },
        "imagen_url": {
          "name": "imagen_url",
          "type": "text",
          "primaryKey": false,
          "notNull": false
        },
        "activo": {
          "name": "activo",
          "type": "boolean",
          "primaryKey": false,
          "notNull": true,
          "default": true
        },
        "created_at": {
          "name": "created_at",
          "type": "timestamp",
          "primaryKey": false,
          "notNull": true,
          "default": "now()"
        },
        "updated_at": {
          "name": "updated_at",
          "type": "timestamp",
          "primaryKey": false,
          "notNull": true,
          "default": "now()"
        }
      },
      "indexes": {},
      "foreignKeys": {},
      "compositePrimaryKeys": {},
      "uniqueConstraints": {},
      "policies": {},
      "checkConstraints": {},
      "isRLSEnabled": false
    },
    "public.galeria_albumes": {
      "name": "galeria_albumes",
      "schema": "",
      "columns": {
        "id": {
          "name": "id",
          "type": "serial",
          "primaryKey": true,
          "notNull": true
        },
        "titulo": {
          "name": "titulo",
          "type": "varchar(100)",
          "primaryKey": false,
          "notNull": true
        },
        "descripcion": {
          "name": "descripcion",
          "type": "varchar(300)",
          "primaryKey": false,
          "notNull": false
        },
        "portada_url": {
          "name": "portada_url",
          "type": "text",
          "primaryKey": false,
          "notNull": false
        },
        "fecha": {
          "name": "fecha",
          "type": "date",
          "primaryKey": false,
          "notNull": false
        },
        "orden": {
          "name": "orden",
          "type": "integer",
          "primaryKey": false,
          "notNull": true,
          "default": 0
        },
        "activo": {
          "name": "activo",
          "type": "boolean",
          "primaryKey": false,
          "notNull": true,
          "default": true
        },
        "created_at": {
          "name": "created_at",
          "type": "timestamp",
          "primaryKey": false,
          "notNull": true,
          "default": "now()"
        },
        "updated_at": {
          "name": "updated_at",
          "type": "timestamp",
          "primaryKey": false,
          "notNull": true,
          "default": "now()"
        }
      },
      "indexes": {},
      "foreignKeys": {},
      "compositePrimaryKeys": {},
      "uniqueConstraints": {},
      "policies": {},
      "checkConstraints": {},
      "isRLSEnabled": false
    },
    "public.galeria_fotos": {
      "name": "galeria_fotos",
      "schema": "",
      "columns": {
        "id": {
          "name": "id",
          "type": "serial",
          "primaryKey": true,
          "notNull": true
        },
        "album_id": {
          "name": "album_id",
          "type": "integer",
          "primaryKey": false,
          "notNull": true
        },
        "tipo": {
          "name": "tipo",
          "type": "varchar(20)",
          "primaryKey": false,
          "notNull": true,
          "default": "'imagen'"
        },
        "imagen_url": {
          "name": "imagen_url",
          "type": "text",
          "primaryKey": false,
          "notNull": true
        },
        "video_url": {
          "name": "video_url",
          "type": "text",
          "primaryKey": false,
          "notNull": false
        },
        "caption": {
          "name": "caption",
          "type": "varchar(150)",
          "primaryKey": false,
          "notNull": false
        },
        "orden": {
          "name": "orden",
          "type": "integer",
          "primaryKey": false,
          "notNull": true,
          "default": 0
        },
        "created_at": {
          "name": "created_at",
          "type": "timestamp",
          "primaryKey": false,
          "notNull": true,
          "default": "now()"
        }
      },
      "indexes": {},
      "foreignKeys": {},
      "compositePrimaryKeys": {},
      "uniqueConstraints": {},
      "policies": {},
      "checkConstraints": {},
      "isRLSEnabled": false
    },
    "public.journal": {
      "name": "journal",
      "schema": "",
      "columns": {
        "id": {
          "name": "id",
          "type": "serial",
          "primaryKey": true,
          "notNull": true
        },
        "titulo": {
          "name": "titulo",
          "type": "varchar(120)",
          "primaryKey": false,
          "notNull": true
        },
        "slug": {
          "name": "slug",
          "type": "varchar(150)",
          "primaryKey": false,
          "notNull": true
        },
        "categoria_id": {
          "name": "categoria_id",
          "type": "integer",
          "primaryKey": false,
          "notNull": false
        },
        "autor_id": {
          "name": "autor_id",
          "type": "integer",
          "primaryKey": false,
          "notNull": false
        },
        "extracto": {
          "name": "extracto",
          "type": "varchar(200)",
          "primaryKey": false,
          "notNull": true
        },
        "contenido": {
          "name": "contenido",
          "type": "text",
          "primaryKey": false,
          "notNull": true
        },
        "imagen_url": {
          "name": "imagen_url",
          "type": "text",
          "primaryKey": false,
          "notNull": false
        },
        "publicado": {
          "name": "publicado",
          "type": "boolean",
          "primaryKey": false,
          "notNull": true,
          "default": false
        },
        "created_at": {
          "name": "created_at",
          "type": "timestamp",
          "primaryKey": false,
          "notNull": true,
          "default": "now()"
        },
        "updated_at": {
          "name": "updated_at",
          "type": "timestamp",
          "primaryKey": false,
          "notNull": true,
          "default": "now()"
        }
      },
      "indexes": {},
      "foreignKeys": {
        "journal_categoria_id_journal_categorias_id_fk": {
          "name": "journal_categoria_id_journal_categorias_id_fk",
          "tableFrom": "journal",
          "tableTo": "journal_categorias",
          "columnsFrom": [
            "categoria_id"
          ],
          "columnsTo": [
            "id"
          ],
          "onDelete": "no action",
          "onUpdate": "no action"
        },
        "journal_autor_id_journal_autores_id_fk": {
          "name": "journal_autor_id_journal_autores_id_fk",
          "tableFrom": "journal",
          "tableTo": "journal_autores",
          "columnsFrom": [
            "autor_id"
          ],
          "columnsTo": [
            "id"
          ],
          "onDelete": "no action",
          "onUpdate": "no action"
        }
      },
      "compositePrimaryKeys": {},
      "uniqueConstraints": {
        "journal_slug_unique": {
          "name": "journal_slug_unique",
          "nullsNotDistinct": false,
          "columns": [
            "slug"
          ]
        }
      },
      "policies": {},
      "checkConstraints": {},
      "isRLSEnabled": false
    },
    "public.journal_autores": {
      "name": "journal_autores",
      "schema": "",
      "columns": {
        "id": {
          "name": "id",
          "type": "serial",
          "primaryKey": true,
          "notNull": true
        },
        "nombre": {
          "name": "nombre",
          "type": "varchar(100)",
          "primaryKey": false,
          "notNull": true
        },
        "cargo": {
          "name": "cargo",
          "type": "varchar(100)",
          "primaryKey": false,
          "notNull": true
        },
        "correo_institucional": {
          "name": "correo_institucional",
          "type": "varchar(255)",
          "primaryKey": false,
          "notNull": false
        },
        "foto_url": {
          "name": "foto_url",
          "type": "text",
          "primaryKey": false,
          "notNull": false
        },
        "created_at": {
          "name": "created_at",
          "type": "timestamp",
          "primaryKey": false,
          "notNull": true,
          "default": "now()"
        }
      },
      "indexes": {},
      "foreignKeys": {},
      "compositePrimaryKeys": {},
      "uniqueConstraints": {},
      "policies": {},
      "checkConstraints": {},
      "isRLSEnabled": false
    },
    "public.journal_categorias": {
      "name": "journal_categorias",
      "schema": "",
      "columns": {
        "id": {
          "name": "id",
          "type": "serial",
          "primaryKey": true,
          "notNull": true
        },
        "nombre": {
          "name": "nombre",
          "type": "varchar(100)",
          "primaryKey": false,
          "notNull": true
        },
        "orden": {
          "name": "orden",
          "type": "integer",
          "primaryKey": false,
          "notNull": true,
          "default": 0
        },
        "created_at": {
          "name": "created_at",
          "type": "timestamp",
          "primaryKey": false,
          "notNull": true,
          "default": "now()"
        }
      },
      "indexes": {},
      "foreignKeys": {},
      "compositePrimaryKeys": {},
      "uniqueConstraints": {},
      "policies": {},
      "checkConstraints": {},
      "isRLSEnabled": false
    },
    "public.matricula_config": {
      "name": "matricula_config",
      "schema": "",
      "columns": {
        "id": {
          "name": "id",
          "type": "serial",
          "primaryKey": true,
          "notNull": true
        },
        "periodo_nuevos_inicio": {
          "name": "periodo_nuevos_inicio",
          "type": "date",
          "primaryKey": false,
          "notNull": false
        },
        "periodo_nuevos_fin": {
          "name": "periodo_nuevos_fin",
          "type": "date",
          "primaryKey": false,
          "notNull": false
        },
        "periodo_antiguos_inicio": {
          "name": "periodo_antiguos_inicio",
          "type": "date",
          "primaryKey": false,
          "notNull": false
        },
        "periodo_antiguos_fin": {
          "name": "periodo_antiguos_fin",
          "type": "date",
          "primaryKey": false,
          "notNull": false
        },
        "enlace_formulario_nuevos": {
          "name": "enlace_formulario_nuevos",
          "type": "text",
          "primaryKey": false,
          "notNull": false
        },
        "enlace_formulario_antiguos": {
          "name": "enlace_formulario_antiguos",
          "type": "text",
          "primaryKey": false,
          "notNull": false
        },
        "requisitos": {
          "name": "requisitos",
          "type": "jsonb",
          "primaryKey": false,
          "notNull": false
        },
        "mensajes_antiguos": {
          "name": "mensajes_antiguos",
          "type": "jsonb",
          "primaryKey": false,
          "notNull": true,
          "default": "'[]'::jsonb"
        },
        "mensajes_nuevos": {
          "name": "mensajes_nuevos",
          "type": "jsonb",
          "primaryKey": false,
          "notNull": true,
          "default": "'[]'::jsonb"
        },
        "mensaje_informativo": {
          "name": "mensaje_informativo",
          "type": "text",
          "primaryKey": false,
          "notNull": false
        },
        "activo": {
          "name": "activo",
          "type": "boolean",
          "primaryKey": false,
          "notNull": true,
          "default": true
        },
        "updated_at": {
          "name": "updated_at",
          "type": "timestamp",
          "primaryKey": false,
          "notNull": true,
          "default": "now()"
        }
      },
      "indexes": {},
      "foreignKeys": {},
      "compositePrimaryKeys": {},
      "uniqueConstraints": {},
      "policies": {},
      "checkConstraints": {},
      "isRLSEnabled": false
    },
    "public.mensajes_contacto": {
      "name": "mensajes_contacto",
      "schema": "",
      "columns": {
        "id": {
          "name": "id",
          "type": "serial",
          "primaryKey": true,
          "notNull": true
        },
        "nombre": {
          "name": "nombre",
          "type": "varchar(100)",
          "primaryKey": false,
          "notNull": true
        },
        "email": {
          "name": "email",
          "type": "varchar(255)",
          "primaryKey": false,
          "notNull": true
        },
        "telefono": {
          "name": "telefono",
          "type": "varchar(20)",
          "primaryKey": false,
          "notNull": false
        },
        "asunto": {
          "name": "asunto",
          "type": "varchar(50)",
          "primaryKey": false,
          "notNull": true
        },
        "mensaje": {
          "name": "mensaje",
          "type": "text",
          "primaryKey": false,
          "notNull": true
        },
        "leido": {
          "name": "leido",
          "type": "boolean",
          "primaryKey": false,
          "notNull": true,
          "default": false
        },
        "respondido": {
          "name": "respondido",
          "type": "boolean",
          "primaryKey": false,
          "notNull": true,
          "default": false
        },
        "created_at": {
          "name": "created_at",
          "type": "timestamp",
          "primaryKey": false,
          "notNull": true,
          "default": "now()"
        }
      },
      "indexes": {},
      "foreignKeys": {},
      "compositePrimaryKeys": {},
      "uniqueConstraints": {},
      "policies": {},
      "checkConstraints": {},
      "isRLSEnabled": false
    },
    "public.pagina_secciones": {
      "name": "pagina_secciones",
      "schema": "",
      "columns": {
        "id": {
          "name": "id",
          "type": "serial",
          "primaryKey": true,
          "notNull": true
        },
        "pagina_id": {
          "name": "pagina_id",
          "type": "integer",
          "primaryKey": false,
          "notNull": true
        },
        "tipo_bloque": {
          "name": "tipo_bloque",
          "type": "varchar(50)",
          "primaryKey": false,
          "notNull": true
        },
        "orden": {
          "name": "orden",
          "type": "integer",
          "primaryKey": false,
          "notNull": true,
          "default": 0
        },
        "configuracion": {
          "name": "configuracion",
          "type": "jsonb",
          "primaryKey": false,
          "notNull": true,
          "default": "'{}'::jsonb"
        },
        "estado_activo": {
          "name": "estado_activo",
          "type": "boolean",
          "primaryKey": false,
          "notNull": true,
          "default": true
        },
        "created_at": {
          "name": "created_at",
          "type": "timestamp",
          "primaryKey": false,
          "notNull": true,
          "default": "now()"
        },
        "updated_at": {
          "name": "updated_at",
          "type": "timestamp",
          "primaryKey": false,
          "notNull": true,
          "default": "now()"
        }
      },
      "indexes": {},
      "foreignKeys": {
        "pagina_secciones_pagina_id_paginas_id_fk": {
          "name": "pagina_secciones_pagina_id_paginas_id_fk",
          "tableFrom": "pagina_secciones",
          "tableTo": "paginas",
          "columnsFrom": [
            "pagina_id"
          ],
          "columnsTo": [
            "id"
          ],
          "onDelete": "cascade",
          "onUpdate": "no action"
        }
      },
      "compositePrimaryKeys": {},
      "uniqueConstraints": {},
      "policies": {},
      "checkConstraints": {},
      "isRLSEnabled": false
    },
    "public.paginas": {
      "name": "paginas",
      "schema": "",
      "columns": {
        "id": {
          "name": "id",
          "type": "serial",
          "primaryKey": true,
          "notNull": true
        },
        "titulo": {
          "name": "titulo",
          "type": "varchar(150)",
          "primaryKey": false,
          "notNull": true
        },
        "slug": {
          "name": "slug",
          "type": "varchar(150)",
          "primaryKey": false,
          "notNull": true
        },
        "activo": {
          "name": "activo",
          "type": "boolean",
          "primaryKey": false,
          "notNull": true,
          "default": true
        },
        "mostrar_en_menu": {
          "name": "mostrar_en_menu",
          "type": "boolean",
          "primaryKey": false,
          "notNull": true,
          "default": true
        },
        "orden_menu": {
          "name": "orden_menu",
          "type": "integer",
          "primaryKey": false,
          "notNull": true,
          "default": 0
        },
        "seo_description": {
          "name": "seo_description",
          "type": "varchar(300)",
          "primaryKey": false,
          "notNull": false
        },
        "created_at": {
          "name": "created_at",
          "type": "timestamp",
          "primaryKey": false,
          "notNull": true,
          "default": "now()"
        },
        "updated_at": {
          "name": "updated_at",
          "type": "timestamp",
          "primaryKey": false,
          "notNull": true,
          "default": "now()"
        }
      },
      "indexes": {},
      "foreignKeys": {},
      "compositePrimaryKeys": {},
      "uniqueConstraints": {
        "paginas_slug_unique": {
          "name": "paginas_slug_unique",
          "nullsNotDistinct": false,
          "columns": [
            "slug"
          ]
        }
      },
      "policies": {},
      "checkConstraints": {},
      "isRLSEnabled": false
    },
    "public.popups": {
      "name": "popups",
      "schema": "",
      "columns": {
        "id": {
          "name": "id",
          "type": "serial",
          "primaryKey": true,
          "notNull": true
        },
        "titulo": {
          "name": "titulo",
          "type": "varchar(80)",
          "primaryKey": false,
          "notNull": true
        },
        "contenido": {
          "name": "contenido",
          "type": "text",
          "primaryKey": false,
          "notNull": true
        },
        "imagen_url": {
          "name": "imagen_url",
          "type": "text",
          "primaryKey": false,
          "notNull": false
        },
        "tipo": {
          "name": "tipo",
          "type": "varchar(20)",
          "primaryKey": false,
          "notNull": true
        },
        "boton_texto": {
          "name": "boton_texto",
          "type": "varchar(50)",
          "primaryKey": false,
          "notNull": false
        },
        "boton_url": {
          "name": "boton_url",
          "type": "text",
          "primaryKey": false,
          "notNull": false
        },
        "posicion": {
          "name": "posicion",
          "type": "varchar(50)",
          "primaryKey": false,
          "notNull": true,
          "default": "'inferior-derecha'"
        },
        "estilo_imagen": {
          "name": "estilo_imagen",
          "type": "varchar(50)",
          "primaryKey": false,
          "notNull": true,
          "default": "'encabezado'"
        },
        "color_fondo": {
          "name": "color_fondo",
          "type": "varchar(50)",
          "primaryKey": false,
          "notNull": true,
          "default": "'#ffffff'"
        },
        "color_texto": {
          "name": "color_texto",
          "type": "varchar(50)",
          "primaryKey": false,
          "notNull": true,
          "default": "'#111827'"
        },
        "tamano_titulo": {
          "name": "tamano_titulo",
          "type": "varchar(20)",
          "primaryKey": false,
          "notNull": true,
          "default": "'md'"
        },
        "fecha_inicio": {
          "name": "fecha_inicio",
          "type": "date",
          "primaryKey": false,
          "notNull": true
        },
        "fecha_fin": {
          "name": "fecha_fin",
          "type": "date",
          "primaryKey": false,
          "notNull": true
        },
        "activo": {
          "name": "activo",
          "type": "boolean",
          "primaryKey": false,
          "notNull": true,
          "default": true
        },
        "frecuencia": {
          "name": "frecuencia",
          "type": "varchar(20)",
          "primaryKey": false,
          "notNull": true
        },
        "prioridad": {
          "name": "prioridad",
          "type": "integer",
          "primaryKey": false,
          "notNull": true,
          "default": 5
        },
        "created_at": {
          "name": "created_at",
          "type": "timestamp",
          "primaryKey": false,
          "notNull": true,
          "default": "now()"
        },
        "updated_at": {
          "name": "updated_at",
          "type": "timestamp",
          "primaryKey": false,
          "notNull": true,
          "default": "now()"
        }
      },
      "indexes": {},
      "foreignKeys": {},
      "compositePrimaryKeys": {},
      "uniqueConstraints": {},
      "policies": {},
      "checkConstraints": {},
      "isRLSEnabled": false
    }
  },
  "enums": {},
  "schemas": {},
  "sequences": {},
  "roles": {},
  "policies": {},
  "views": {},
  "_meta": {
    "columns": {},
    "schemas": {},
    "tables": {}
  }
}